Plametal_calc/calc.py
Plametal_calc-0.0.2.dist-info/LICENSE
Plametal_calc-0.0.2.dist-info/METADATA
Plametal_calc-0.0.2.dist-info/WHEEL
Plametal_calc-0.0.2.dist-info/top_level.txt
Plametal_calc-0.0.2.dist-info/RECORD
