Metadata-Version: 2.1
Name: Plametal-calc
Version: 0.0.2
Summary: practice
Home-page: https://github.com/Plametal/oss/archive/refs/tags/v1.0.0.zip
Download-URL: https://github.com/Plametal/oss/archive/refs/tags/v1.0.0.zip
Author: Plametal
License-File: LICENSE
